de_pytools/__init__.py
de_pytools/aws/__init__.py
de_pytools/aws/s3.py
de_pytools/oracle/__init__.py
de_pytools/snowflake/__init__.py
de_pytools-0.0.3.dist-info/LICENSE.txt
de_pytools-0.0.3.dist-info/METADATA
de_pytools-0.0.3.dist-info/WHEEL
de_pytools-0.0.3.dist-info/top_level.txt
de_pytools-0.0.3.dist-info/RECORD
